setup.py
lessrpc_msgpack/__init__.py
lessrpc_msgpack/lessmsgpack.py
lessrpc_msgpack.egg-info/PKG-INFO
lessrpc_msgpack.egg-info/SOURCES.txt
lessrpc_msgpack.egg-info/dependency_links.txt
lessrpc_msgpack.egg-info/requires.txt
lessrpc_msgpack.egg-info/top_level.txt