Metadata-Version: 1.1
Name: lessrpc-msgpack
Version: 1.0.4
Summary: Less RPC MsgPack extension
Home-page: https://github.com/LessRPC/less_msgpack/
Author: Salim Malakouti
Author-email: salim.malakouti@gmail.com
License: MIT
Download-URL: https://github.com/LessRPC/less_msgpack/archive/1.0.4.tar.gz
Keywords: python,serialization,deserialization,rpc,rmi,less rpc,client,server
Platform: UNKNOWN
Classifier: Programming Language :: Python
